{
    "all": [
        {
            "name"          : "Joe Henderson",
            "comment"       : "Lorem ipsum, dolor sit amet consectetur adipisicing elit. Voluptatem necessitatibus accusamus numquam eaque nihil architecto eius commodi temporibus quos! Veritatis expedita ipsa, nam accusantium maiores fuga! Beatae repellat quidem et.",
            "date"          : "3 days ago",
            "reply"         : 0,
            "likes"         : "5"
        },
        {
            "name"          : "Jane Doe",
            "comment"       : "Lorem ipsum dolor sit amet consectetur adipisicing elit. Magni illum quae officiis quasi, enim sequi qui dicta explicabo provident optio est voluptates in, veniam corporis quas debitis exercitationem aut quisquam!",
            "date"          : "2 hours ago",
            "reply"         : 1,
            "reply_name"    : "Joe Henderson",
            "likes"         : null
        }
    ]
}